dict2xlsx/__init__.py
dict2xlsx/dict2xlsx.py
dict2xlsx-0.0.1.dist-info/LICENSE
dict2xlsx-0.0.1.dist-info/METADATA
dict2xlsx-0.0.1.dist-info/WHEEL
dict2xlsx-0.0.1.dist-info/top_level.txt
dict2xlsx-0.0.1.dist-info/RECORD
