Metadata-Version: 2.1
Name: dict2xlsx
Version: 0.0.1
Summary: Python Package to convert dict to xlsx
Home-page: https://github.com/Satyam-2001/dict2xlsx
Author: Satyam Lohiya
Author-email: lohiyasatyam@gmail.com
License: MIT
Keywords: excel,dict-to-xlsx,convert,dict2xlsx
Classifier: Development Status :: 4 - Beta
Classifier: Intended Audience :: Developers
Classifier: License :: OSI Approved :: MIT License
Classifier: Operating System :: Unix
Classifier: Operating System :: POSIX :: Linux
Classifier: Operating System :: MacOS
Classifier: Operating System :: Microsoft :: Windows
Classifier: Programming Language :: Python :: 2.7
Classifier: Programming Language :: Python :: 3
Classifier: Programming Language :: Python :: 3.6
License-File: LICENSE
Requires-Dist: openpyxl
